<document>
	<Panel name="panel" x="0.15" y="0.1" width="0.7" height="0.8" image="windows/titled.png" >
		<Label name="SelectLabel" text="Select ship" alignment="center" y="0.05" width="0.6" height="0.05" />

		<Label name="features1" text="Features:" font-size="20" font-color="0.3 0.88 0.4 0.8" x="0.1" y="0.15" width="0" height="0.05" />
		<Label name="features2" text="- fast shooting" font-size="20" font-color="0.3 0.88 0.4 0.8" x="0.1" y="0.2" width="0" height="0.05" />
		<Label name="features3" text="- shield queue" font-size="20" font-color="0.3 0.88 0.4 0.8" x="0.1" y="0.25" width="0" height="0.05" />

		<Image name="bankImg" image="energybar.png" x="0.7" y="0.15" width="0.25" height="-0.41" >
			<Label name="bank" text="123456" font-size="20" font-color="0.9 0.88 0.4 0.8" x="0.246" y="0.458" width="0.68" height="0.36" />
		</Image>

		<Button name="left"  x="-0.04" y="0.4" width="0.16" height="-1" image="buttons/prev.png" hoverimage="buttons/prev.png" pressedimage="buttons/prev_pressed.png" />
		<Button name="right"  x="0.88" y="0.4" width="0.16" height="-1" image="buttons/play.png" hoverimage="buttons/play.png" pressedimage="buttons/play_pressed.png" />
	</Panel>

	<Image name="costlogo" image="energy.png" x="0.43" y="0.63" width="0.05" height="-1.34"  />
	<Label name="cost" text="5000" font-size="25" font-color="0.3 0.88 0.4 0.8"  x="0.48" y="0.63" width="0" height="0.11" />

	<Button name="back"  x="0.3" y="0.82" width="0.08" height="-1" image="buttons/back.png" hoverimage="buttons/back_hover.png" pressedimage="buttons/back_pressed.png" />
	<Button name="start" text="Start" alignment="center" y="0.7" width="0.4" height="0.12" />
</document>